etb_pdf/PDF.py
etb_pdf/__init__.py
etb_pdf-0.1.2.dist-info/LICENSE
etb_pdf-0.1.2.dist-info/METADATA
etb_pdf-0.1.2.dist-info/WHEEL
etb_pdf-0.1.2.dist-info/RECORD
