Metadata-Version: 2.1
Name: etb-pdf
Version: 0.1.2
Summary: Fill in PDF forms
License: MIT
Author: Tate Button
Author-email: yg3bpwn0or679hau8fxi@duck.com
Requires-Python: >=3.10,<4.0
Classifier: License :: OSI Approved :: MIT License
Classifier: Programming Language :: Python :: 3
Classifier: Programming Language :: Python :: 3.10
Classifier: Programming Language :: Python :: 3.11
Classifier: Programming Language :: Python :: 3.12
Requires-Dist: pypdf2 (>=3.0.1,<4.0.0)
